gibberifire/__init__.py
gibberifire/__main__.py
gibberifire/asynchronous/__init__.py
gibberifire/asynchronous/gibberifire.py
gibberifire/cli/__init__.py
gibberifire/cli/config.py
gibberifire/cli/main.py
gibberifire/core/__init__.py
gibberifire/core/exceptions.py
gibberifire/core/gibberifire.py
gibberifire/core/models.py
gibberifire/data/__init__.py
gibberifire/data/bidi.py
gibberifire/data/combining.py
gibberifire/data/confusables.py
gibberifire/data/emoji_alphabet.py
gibberifire/data/zwsp_chars.py
gibberifire/methods/__init__.py
gibberifire/methods/base.py
gibberifire/methods/bidi.py
gibberifire/methods/combining.py
gibberifire/methods/encoding.py
gibberifire/methods/homoglyph.py
gibberifire/methods/zwsp.py
gibberifire-0.1.0.dist-info/WHEEL
gibberifire-0.1.0.dist-info/entry_points.txt
gibberifire-0.1.0.dist-info/METADATA
gibberifire-0.1.0.dist-info/RECORD
