Metadata-Version: 2.3
Name: gibberifire
Version: 0.1.0
Summary: Protect text from AI using invisible Unicode characters
Keywords: unicode,ai,protection,invisible,text,obfuscation
Author: Vlad Gavrilov
Author-email: Vlad Gavrilov <vlad.gavrilov.dev@gmail.com>
License: MIT License
Classifier: Development Status :: 3 - Alpha
Classifier: Intended Audience :: Developers
Classifier: License :: OSI Approved :: MIT License
Classifier: Programming Language :: Python :: 3
Classifier: Programming Language :: Python :: 3.10
Classifier: Programming Language :: Python :: 3.11
Classifier: Programming Language :: Python :: 3.12
Classifier: Programming Language :: Python :: 3.13
Classifier: Programming Language :: Python :: 3.14
Classifier: Topic :: Text Processing
Classifier: Topic :: Security
Classifier: Typing :: Typed
Requires-Dist: pydantic>=2.12.5
Requires-Dist: pyyaml>=6.0.3
Requires-Dist: pytest>=8.0 ; extra == 'dev'
Requires-Dist: pytest-asyncio>=0.23 ; extra == 'dev'
Requires-Dist: pytest-cov>=4.1 ; extra == 'dev'
Requires-Dist: ruff>=0.2 ; extra == 'dev'
Requires-Dist: pre-commit>=4.5.0 ; extra == 'dev'
Requires-Dist: twine>=6.0.1 ; extra == 'dev'
Requires-Python: >=3.10
Project-URL: Changelog, https://github.com/vlad-gavrilov/gibberifire/blob/master/CHANGELOG.md
Project-URL: Documentation, https://github.com/vlad-gavrilov/gibberifire/blob/master/docs/DEEP_DIVE.md
Project-URL: Homepage, https://github.com/vlad-gavrilov/gibberifire#readme
Project-URL: Issues, https://github.com/vlad-gavrilov/gibberifire/issues
Project-URL: Source, https://github.com/vlad-gavrilov/gibberifire
Provides-Extra: dev
